cledar/__init__.py
cledar/kafka/README.md
cledar/kafka/__init__.py
cledar/kafka/exceptions.py
cledar/kafka/logger.py
cledar/kafka/clients/base.py
cledar/kafka/clients/consumer.py
cledar/kafka/clients/producer.py
cledar/kafka/config/schemas.py
cledar/kafka/handlers/dead_letter.py
cledar/kafka/handlers/parser.py
cledar/kafka/models/input.py
cledar/kafka/models/message.py
cledar/kafka/models/output.py
cledar/kafka/tests/.env.test.kafka
cledar/kafka/tests/README.md
cledar/kafka/tests/conftest.py
cledar/kafka/tests/integration/__init__.py
cledar/kafka/tests/integration/conftest.py
cledar/kafka/tests/integration/helpers.py
cledar/kafka/tests/integration/test_consumer_integration.py
cledar/kafka/tests/integration/test_integration.py
cledar/kafka/tests/integration/test_producer_consumer_interaction.py
cledar/kafka/tests/integration/test_producer_integration.py
cledar/kafka/tests/unit/__init__.py
cledar/kafka/tests/unit/test_base_kafka_client.py
cledar/kafka/tests/unit/test_config_validation.py
cledar/kafka/tests/unit/test_dead_letter_handler.py
cledar/kafka/tests/unit/test_error_handling.py
cledar/kafka/tests/unit/test_input_parser.py
cledar/kafka/tests/unit/test_input_parser_comprehensive.py
cledar/kafka/tests/unit/test_utils.py
cledar/kafka/tests/unit/test_utils_comprehensive.py
cledar/kafka/utils/callbacks.py
cledar/kafka/utils/messages.py
cledar/kafka/utils/topics.py
cledar/kserve/README.md
cledar/kserve/__init__.py
cledar/kserve/utils.py
cledar/kserve/tests/__init__.py
cledar/kserve/tests/test_utils.py
cledar/logging/README.md
cledar/logging/__init__.py
cledar/logging/universal_plaintext_formatter.py
cledar/logging/tests/test_universal_plaintext_formatter.py
cledar/monitoring/README.md
cledar/monitoring/__init__.py
cledar/monitoring/monitoring_server.py
cledar/monitoring/tests/test_monitoring_server.py
cledar/monitoring/tests/integration/test_monitoring_server_int.py
cledar/nonce/README.md
cledar/nonce/__init__.py
cledar/nonce/nonce_service.py
cledar_sdk-2.0.3.dist-info/METADATA
cledar_sdk-2.0.3.dist-info/WHEEL
cledar_sdk-2.0.3.dist-info/licenses/LICENSE
cledar_sdk-2.0.3.dist-info/RECORD
