Metadata-Version: 2.4
Name: cledar-sdk
Version: 2.0.3
Summary: Cledar Python SDK
Author: Cledar
License-File: LICENSE
Requires-Python: >=3.12.7
Requires-Dist: adlfs>=2025.8.0
Requires-Dist: boto3-stubs>=1.34.138
Requires-Dist: boto3>=1.34.138
Requires-Dist: confluent-kafka>=2.4.0
Requires-Dist: ecs-logging>=2.1.0
Requires-Dist: fastapi>=0.112.3
Requires-Dist: fsspec>=2025.9.0
Requires-Dist: prometheus-client>=0.20.0
Requires-Dist: pydantic-settings>=2.3.3
Requires-Dist: pydantic>=2.7.0
Requires-Dist: redis>=5.2.1
Requires-Dist: s3fs>=2025.9.0
Requires-Dist: uvicorn>=0.30.6
